audioevals/__init__.py
audioevals/gen_audios.py
audioevals/py.typed
audioevals/run_evals.py
audioevals/tts.py
audioevals/evals/audiobox_eval.py
audioevals/evals/vad_eval.py
audioevals/evals/wer_eval.py
audioevals/utils/audio.py
audioevals/utils/common.py
audioevals/utils/vad/silero.py
audioevals/utils/vad/silero_vad_v5_0.onnx
audioevals-0.3.0.dist-info/METADATA
audioevals-0.3.0.dist-info/WHEEL
audioevals-0.3.0.dist-info/entry_points.txt
audioevals-0.3.0.dist-info/RECORD
