Metadata-Version: 2.4
Name: audioevals
Version: 0.3.0
Summary: Effective evaluations for Text-to-Speech (TTS) systems
Author-email: Sayan Jyoti Das <sayanjyotidasworkmail@gmail.com>
Requires-Python: >=3.12
Requires-Dist: aiohttp>=3.12.14
Requires-Dist: audiobox-aesthetics>=0.0.4
Requires-Dist: av>=15.0.0
Requires-Dist: jiwer>=4.0.0
Requires-Dist: numpy>=2.3.1
Requires-Dist: onnxruntime>=1.22.1
Requires-Dist: pydub>=0.25.1
Requires-Dist: soundfile>=0.13.1
Requires-Dist: soxr>=0.5.0.post1
